ymp/__init__.py
ymp/__main__.py
ymp/_version.py
ymp/blast.py
ymp/blast2gff.py
ymp/cache.py
ymp/cluster.py
ymp/common.py
ymp/config.py
ymp/coverage.rules
ymp/dna.py
ymp/download.py
ymp/env.py
ymp/exceptions.py
ymp/gff.py
ymp/helpers.py
ymp/map2otu.py
ymp/nuc2aa.py
ymp/snakemake.py
ymp/snakemakelexer.py
ymp/sphinxext.py
ymp/string.py
ymp/util.py
ymp/yaml.py
ymp/R/CAGs.Rmd
ymp/R/ballgown_collect.R
ymp/R/blast.Rmd
ymp/cli/__init__.py
ymp/cli/env.py
ymp/cli/init.py
ymp/cli/make.py
ymp/cli/scan.py
ymp/cli/shared_options.py
ymp/cli/show.py
ymp/cli/stage.py
ymp/conda_envs/latest/README.md
ymp/conda_envs/latest/linux/ballgown.txt
ymp/conda_envs/latest/linux/ballgown.yml
ymp/conda_envs/latest/linux/bbmap.txt
ymp/conda_envs/latest/linux/bbmap.yml
ymp/conda_envs/latest/linux/bedtools.txt
ymp/conda_envs/latest/linux/bedtools.yml
ymp/conda_envs/latest/linux/biom_format.txt
ymp/conda_envs/latest/linux/biom_format.yml
ymp/conda_envs/latest/linux/blast.txt
ymp/conda_envs/latest/linux/blast.yml
ymp/conda_envs/latest/linux/blat.txt
ymp/conda_envs/latest/linux/blat.yml
ymp/conda_envs/latest/linux/bmtagger.txt
ymp/conda_envs/latest/linux/bmtagger.yml
ymp/conda_envs/latest/linux/bowtie2.txt
ymp/conda_envs/latest/linux/bowtie2.yml
ymp/conda_envs/latest/linux/cdhit.txt
ymp/conda_envs/latest/linux/cdhit.yml
ymp/conda_envs/latest/linux/centrifuge.txt
ymp/conda_envs/latest/linux/centrifuge.yml
ymp/conda_envs/latest/linux/diamond.txt
ymp/conda_envs/latest/linux/diamond.yml
ymp/conda_envs/latest/linux/fa2fq.txt
ymp/conda_envs/latest/linux/fa2fq.yml
ymp/conda_envs/latest/linux/fastq-multx.txt
ymp/conda_envs/latest/linux/fastq-multx.yml
ymp/conda_envs/latest/linux/fastqc.txt
ymp/conda_envs/latest/linux/fastqc.yml
ymp/conda_envs/latest/linux/hisat2.txt
ymp/conda_envs/latest/linux/hisat2.yml
ymp/conda_envs/latest/linux/humann2.txt
ymp/conda_envs/latest/linux/humann2.yml
ymp/conda_envs/latest/linux/megahit.txt
ymp/conda_envs/latest/linux/megahit.yml
ymp/conda_envs/latest/linux/metabat2.txt
ymp-0.3.2.dist-info/licenses/LICENSE
ymp-0.3.2.dist-info/METADATA
ymp-0.3.2.dist-info/WHEEL
ymp-0.3.2.dist-info/entry_points.txt
ymp-0.3.2.dist-info/top_level.txt
ymp-0.3.2.dist-info/RECORD
