Metadata-Version: 2.4
Name: ymp
Version: 0.3.2
Summary: Flexible multi-omic pipeline system
Home-page: https://github.com/epruesse/ymp
Author: Elmar Pruesse
Author-email: elmar@pruesse.net
License: GPL-3
Project-URL: Documentation, https://ymp.readthedocs.io
Project-URL: Source, https://github.com/epruesse/ymp
Keywords: bioinformatics pipeline workflow automation rnaseq genomics metagenomics conda bioconda snakemake
Platform: linux
Platform: macos
Classifier: Development Status :: 4 - Beta
Classifier: Environment :: Console
Classifier: Intended Audience :: Science/Research
Classifier: License :: OSI Approved :: GNU General Public License v3 or later (GPLv3+)
Classifier: Natural Language :: English
Classifier: Operating System :: MacOS
Classifier: Operating System :: POSIX :: Linux
Classifier: Programming Language :: Python :: 3.6
Classifier: Topic :: Scientific/Engineering :: Bio-Informatics
Requires-Python: >=3.10
License-File: LICENSE
Requires-Dist: snakemake<8,>=7.32
Requires-Dist: click>8
Requires-Dist: click-completion
Requires-Dist: ruamel.yaml>0.15
Requires-Dist: drmaa
Requires-Dist: pandas>=0.20
Requires-Dist: openpyxl
Requires-Dist: coloredlogs
Requires-Dist: xdg
Requires-Dist: aiohttp
Requires-Dist: tqdm>=4.21.0
Provides-Extra: docs
Requires-Dist: sphinx; extra == "docs"
Requires-Dist: cloud_sptheme; extra == "docs"
Requires-Dist: sphinxcontrib-fulltoc; extra == "docs"
Requires-Dist: sphinx-click; extra == "docs"
Requires-Dist: sphinx_autodoc_typehints; extra == "docs"
Requires-Dist: ftputil; extra == "docs"
Dynamic: author
Dynamic: author-email
Dynamic: classifier
Dynamic: description
Dynamic: description-content-type
Dynamic: home-page
Dynamic: keywords
Dynamic: license
Dynamic: license-file
Dynamic: platform
Dynamic: project-url
Dynamic: provides-extra
Dynamic: requires-dist
Dynamic: requires-python
Dynamic: summary
